google/cloud/container/__init__.py
google/cloud/container/gapic_version.py
google/cloud/container/py.typed
google/cloud/container_v1/__init__.py
google/cloud/container_v1/gapic_metadata.json
google/cloud/container_v1/gapic_version.py
google/cloud/container_v1/py.typed
google/cloud/container_v1/services/__init__.py
google/cloud/container_v1/services/cluster_manager/__init__.py
google/cloud/container_v1/services/cluster_manager/async_client.py
google/cloud/container_v1/services/cluster_manager/client.py
google/cloud/container_v1/services/cluster_manager/pagers.py
google/cloud/container_v1/services/cluster_manager/transports/__init__.py
google/cloud/container_v1/services/cluster_manager/transports/base.py
google/cloud/container_v1/services/cluster_manager/transports/grpc.py
google/cloud/container_v1/services/cluster_manager/transports/grpc_asyncio.py
google/cloud/container_v1/services/cluster_manager/transports/rest.py
google/cloud/container_v1/services/cluster_manager/transports/rest_base.py
google/cloud/container_v1/types/__init__.py
google/cloud/container_v1/types/cluster_service.py
google/cloud/container_v1beta1/__init__.py
google/cloud/container_v1beta1/gapic_metadata.json
google/cloud/container_v1beta1/gapic_version.py
google/cloud/container_v1beta1/py.typed
google/cloud/container_v1beta1/services/__init__.py
google/cloud/container_v1beta1/services/cluster_manager/__init__.py
google/cloud/container_v1beta1/services/cluster_manager/async_client.py
google/cloud/container_v1beta1/services/cluster_manager/client.py
google/cloud/container_v1beta1/services/cluster_manager/pagers.py
google/cloud/container_v1beta1/services/cluster_manager/transports/__init__.py
google/cloud/container_v1beta1/services/cluster_manager/transports/base.py
google/cloud/container_v1beta1/services/cluster_manager/transports/grpc.py
google/cloud/container_v1beta1/services/cluster_manager/transports/grpc_asyncio.py
google/cloud/container_v1beta1/types/__init__.py
google_cloud_container-2.63.0.dist-info/licenses/LICENSE
google_cloud_container-2.63.0.dist-info/METADATA
google_cloud_container-2.63.0.dist-info/WHEEL
google_cloud_container-2.63.0.dist-info/top_level.txt
google_cloud_container-2.63.0.dist-info/RECORD
